fastmqtt/__init__.py
fastmqtt/connectors/__init__.py
fastmqtt/connectors/aiomqtt/__init__.py
fastmqtt/connectors/aiomqtt/connector.py
fastmqtt/connectors/aiomqtt/convertors/__init__.py
fastmqtt/connectors/aiomqtt/convertors/message.py
fastmqtt/connectors/aiomqtt/convertors/options.py
fastmqtt/connectors/aiomqtt/convertors/properties.py
fastmqtt/connectors/base.py
fastmqtt/encoders.py
fastmqtt/exceptions.py
fastmqtt/fastmqtt.py
fastmqtt/message_handler.py
fastmqtt/properties.py
fastmqtt/response.py
fastmqtt/router.py
fastmqtt/subscription_manager.py
fastmqtt/types.py
fastmqtt-0.2.1.dist-info/LICENSE
fastmqtt-0.2.1.dist-info/METADATA
fastmqtt-0.2.1.dist-info/WHEEL
fastmqtt-0.2.1.dist-info/RECORD
