Metadata-Version: 2.1
Name: fastmqtt
Version: 0.2.1
Summary: 
Home-page: https://github.com/toxazhl/fastmqtt
Author: toxazhl
Author-email: zhltoxa@gmail.com
Requires-Python: >=3.10,<4.0
Classifier: Programming Language :: Python :: 3
Classifier: Programming Language :: Python :: 3.10
Classifier: Programming Language :: Python :: 3.11
Classifier: Programming Language :: Python :: 3.12
Requires-Dist: aiomqtt (>=2.3.0,<3.0.0)
Requires-Dist: cbor2 (>=5.6.4,<6.0.0)
Requires-Dist: msgpack (>=1.0.8,<2.0.0)
Requires-Dist: orjson (>=3.10.7,<4.0.0)
Requires-Dist: ormsgpack (>=1.5.0,<2.0.0)
Requires-Dist: tenacity (>=9.0.0,<10.0.0)
Project-URL: Repository, https://github.com/toxazhl/fastmqtt
